openapi_client/__init__.py
openapi_client/api_client.py
openapi_client/configuration.py
openapi_client/exceptions.py
openapi_client/model_utils.py
openapi_client/rest.py
openapi_client/api/__init__.py
openapi_client/api/default_api.py
openapi_client/apis/__init__.py
openapi_client/model/__init__.py
openapi_client/model/conservation_status.py
openapi_client/model/defendant.py
openapi_client/model/defendant_post.py
openapi_client/model/http_validation_error.py
openapi_client/model/judgment.py
openapi_client/model/judgment_post.py
openapi_client/model/protection_class.py
openapi_client/model/source.py
openapi_client/model/source_category.py
openapi_client/model/source_post.py
openapi_client/model/species.py
openapi_client/model/species_bulk_patch_result.py
openapi_client/model/species_short.py
openapi_client/model/validation_error.py
openapi_client/models/__init__.py
openapi_client/test/__init__.py
openapi_client/test/test_conservation_status.py
openapi_client/test/test_default_api.py
openapi_client/test/test_defendant.py
openapi_client/test/test_defendant_post.py
openapi_client/test/test_http_validation_error.py
openapi_client/test/test_judgment.py
openapi_client/test/test_judgment_post.py
openapi_client/test/test_protection_class.py
openapi_client/test/test_source.py
openapi_client/test/test_source_category.py
openapi_client/test/test_source_post.py
openapi_client/test/test_species.py
openapi_client/test/test_species_bulk_patch_result.py
openapi_client/test/test_species_short.py
openapi_client/test/test_validation_error.py
passerine_client-0.0.5.dist-info/METADATA
passerine_client-0.0.5.dist-info/WHEEL
passerine_client-0.0.5.dist-info/top_level.txt
passerine_client-0.0.5.dist-info/RECORD
