Metadata-Version: 2.1
Name: passerine-client
Version: 0.0.5
Summary: The API client for the antipoaching platform
Author: Zixuan James Li
Author-email: p359101898@gmail.com
License: UNKNOWN
Platform: UNKNOWN
Requires-Dist: urllib3 (>=1.25.3)
Requires-Dist: python-dateutil
